lumberjack_formatter
