Metadata-Version: 1.1
Name: lumberjack-formatter
Version: 0.1.4
Summary: Python logging framework JSON formatter for use with the lumberjack transport (logstash-forwarder)
Home-page: https://github.com/dyejon/python_lumberjack_formatter
Author: IBM
Author-email: jdye@us.ibm.com
License: UNKNOWN
Download-URL: https://github.com/dyejon/python_lumberjack_formatter/tarball/0.1.4
Platform: UNKNOWN
Provides: lumberjack_formatter
